sigmaepsilon/mesh/__init__.py
sigmaepsilon/mesh/cellapproximator.py
sigmaepsilon/mesh/cells/__init__.py
sigmaepsilon/mesh/cells/h27.py
sigmaepsilon/mesh/cells/h8.py
sigmaepsilon/mesh/cells/l2.py
sigmaepsilon/mesh/cells/l3.py
sigmaepsilon/mesh/cells/q4.py
sigmaepsilon/mesh/cells/q8.py
sigmaepsilon/mesh/cells/q9.py
sigmaepsilon/mesh/cells/t3.py
sigmaepsilon/mesh/cells/t6.py
sigmaepsilon/mesh/cells/tet10.py
sigmaepsilon/mesh/cells/tet4.py
sigmaepsilon/mesh/cells/w18.py
sigmaepsilon/mesh/cells/w6.py
sigmaepsilon/mesh/config.py
sigmaepsilon/mesh/data/__init__.py
sigmaepsilon/mesh/data/akwrapper.py
sigmaepsilon/mesh/data/celldata.py
sigmaepsilon/mesh/data/linedata.py
sigmaepsilon/mesh/data/pointdata.py
sigmaepsilon/mesh/data/polycell.py
sigmaepsilon/mesh/data/polydata.py
sigmaepsilon/mesh/data/trimesh.py
sigmaepsilon/mesh/domains/__init__.py
sigmaepsilon/mesh/domains/section.py
sigmaepsilon/mesh/downloads.py
sigmaepsilon/mesh/errors/__init__.py
sigmaepsilon/mesh/examples.py
sigmaepsilon/mesh/extrude.py
sigmaepsilon/mesh/geometry/__init__.py
sigmaepsilon/mesh/geometry/geometry.py
sigmaepsilon/mesh/grid.py
sigmaepsilon/mesh/helpers.py
sigmaepsilon/mesh/indexmanager.py
sigmaepsilon/mesh/io/__init__.py
sigmaepsilon/mesh/io/from_meshio.py
sigmaepsilon/mesh/io/from_pyvista.py
sigmaepsilon/mesh/io/to_k3d.py
sigmaepsilon/mesh/io/to_pyvista.py
sigmaepsilon/mesh/io/to_vtk.py
sigmaepsilon/mesh/mesh1d.py
sigmaepsilon/mesh/plotting/__init__.py
sigmaepsilon/mesh/plotting/k3dplot.py
sigmaepsilon/mesh/plotting/mpl/__init__.py
sigmaepsilon/mesh/plotting/mpl/parallel.py
sigmaepsilon/mesh/plotting/mpl/triplot.py
sigmaepsilon/mesh/plotting/mpl/utils.py
sigmaepsilon/mesh/plotting/plotly/__init__.py
sigmaepsilon/mesh/plotting/plotly/lines.py
sigmaepsilon/mesh/plotting/plotly/points.py
sigmaepsilon/mesh/plotting/plotly/tri.py
sigmaepsilon/mesh/plotting/pvplot.py
sigmaepsilon/mesh/pop.py
sigmaepsilon/mesh/recipes.py
sigmaepsilon/mesh/space/__init__.py
sigmaepsilon/mesh/space/frame.py
sigmaepsilon_mesh-3.1.0.dist-info/LICENSE
sigmaepsilon_mesh-3.1.0.dist-info/METADATA
sigmaepsilon_mesh-3.1.0.dist-info/WHEEL
sigmaepsilon_mesh-3.1.0.dist-info/RECORD
