Metadata-Version: 2.1
Name: sigmaepsilon.mesh
Version: 3.1.0
Summary: A Python package to build, manipulate and analyze polygonal meshes.
Home-page: https://github.com/sigma-epsilon/sigmaepsilon.mesh
License: MIT
Keywords: engineering,mathematics,optimization,vector,tensor,vector algebra,tensor algebra,symbolic mathematics,nonlinear optimization
Author: Bence Balogh
Author-email: bencebalogh@sigmaepsilon.com
Maintainer: Bence Balogh
Maintainer-email: bencebalogh@sigmaepsilon.com
Requires-Python: >=3.10,<3.13
Classifier: Development Status :: 5 - Production/Stable
Classifier: License :: OSI Approved :: MIT License
Classifier: Operating System :: OS Independent
Classifier: Programming Language :: Python :: 3
Classifier: Programming Language :: Python :: 3.10
Classifier: Programming Language :: Python :: 3.11
Classifier: Programming Language :: Python :: 3.12
Classifier: Programming Language :: Python :: 3 :: Only
Requires-Dist: fsspec (>=2023.1.0,<2024.0.0)
Requires-Dist: meshio (>=5.3.5,<6.0.0)
Requires-Dist: numpy (>=1.22.2)
Requires-Dist: pillow (>=10.3.0)
Requires-Dist: sectionproperties (>2.1.3)
Requires-Dist: sigmaepsilon-deepdict (>=2.0.0,<3.0.0)
Requires-Dist: sigmaepsilon-math (>=2.1.0,<3.0.0)
Requires-Dist: toml (>=0.10.2,<0.11.0)
Project-URL: Documentation, https://sigmaepsilonmath.readthedocs.io/en/latest/?badge=latest
Project-URL: Repository, https://github.com/sigma-epsilon/sigmaepsilon.mesh
